[
    {
        "content": [
            {
                "x": 288.30926787318634,
                "y": 719.6300765120606
            },
            {
                "x": 290.30926787318634,
                "y": 716.6300765120606
            },
            {
                "x": 292.05926787318634,
                "y": 715.0050765120606
            },
            {
                "x": 295.55926787318634,
                "y": 711.7550765120606
            },
            {
                "x": 298.8092678731864,
                "y": 709.7550765120606
            },
            {
                "x": 301.18426787318634,
                "y": 707.8800765120604
            },
            {
                "x": 303.8092678731864,
                "y": 705.0050765120607
            },
            {
                "x": 306.6842678731864,
                "y": 702.6300765120604
            },
            {
                "x": 309.8092678731864,
                "y": 700.3800765120606
            },
            {
                "x": 313.55926787318634,
                "y": 697.7550765120606
            },
            {
                "x": 316.0592678731864,
                "y": 695.5050765120603
            },
            {
                "x": 319.1842678731864,
                "y": 692.8800765120604
            },
            {
                "x": 321.8092678731863,
                "y": 690.3800765120606
            },
            {
                "x": 324.0592678731864,
                "y": 687.7550765120607
            },
            {
                "x": 326.6842678731864,
                "y": 685.3800765120604
            },
            {
                "x": 327.4342678731864,
                "y": 683.5050765120604
            },
            {
                "x": 325.8092678731863,
                "y": 683.5050765120604
            },
            {
                "x": 323.30926787318634,
                "y": 684.7550765120606
            },
            {
                "x": 321.05926787318634,
                "y": 686.6300765120606
            },
            {
                "x": 317.93426787318634,
                "y": 689.6300765120604
            },
            {
                "x": 315.4342678731864,
                "y": 692.1300765120606
            },
            {
                "x": 311.93426787318634,
                "y": 694.8800765120604
            },
            {
                "x": 308.55926787318634,
                "y": 697.3800765120607
            },
            {
                "x": 304.93426787318634,
                "y": 699.6300765120604
            },
            {
                "x": 301.80926787318634,
                "y": 700.8800765120606
            },
            {
                "x": 297.6842678731863,
                "y": 703.1300765120603
            },
            {
                "x": 294.6842678731864,
                "y": 706.1300765120606
            },
            {
                "x": 291.3092678731864,
                "y": 710.2550765120604
            },
            {
                "x": 287.30926787318646,
                "y": 714.0050765120606
            },
            {
                "x": 285.3092678731864,
                "y": 716.8800765120604
            },
            {
                "x": 284.18426787318646,
                "y": 718.7550765120606
            },
            {
                "x": 283.55926787318634,
                "y": 719.8800765120604
            }
        ],
        "rectMask": {
            "xMin": 283.55926787318634,
            "yMin": 683.5050765120604,
            "width": 43.875,
            "height": 36.375
        },
        "labels": {
            "labelName": "unnamed",
            "labelColor": "red",
            "labelColorRGB": "255,0,0",
            "visibility": false
        },
        "labelLocation": {
            "x": 305.49676787318634,
            "y": 701.6925765120604
        },
        "contentType": "polygon"
    },
    {
        "content": [
            {
                "x": 927.3787618727855,
                "y": 719.8268378070491
            },
            {
                "x": 929.006569770126,
                "y": 711.3260632320487
            },
            {
                "x": 930.0917750350196,
                "y": 702.6444211128994
            },
            {
                "x": 931.3578478440622,
                "y": 695.5905868910905
            },
            {
                "x": 932.2621855648069,
                "y": 686.9089447719412
            },
            {
                "x": 935.517801359488,
                "y": 680.7594482708772
            },
            {
                "x": 935.517801359488,
                "y": 673.3438789607704
            },
            {
                "x": 937.6882118892754,
                "y": 664.4813692974723
            },
            {
                "x": 939.3160197866159,
                "y": 655.2571245458761
            },
            {
                "x": 941.4864303164031,
                "y": 646.0328797942799
            },
            {
                "x": 943.8377083903393,
                "y": 636.8086350426839
            },
            {
                "x": 945.4655162876799,
                "y": 628.3078604676836
            },
            {
                "x": 946.3698540084246,
                "y": 621.2540262458748
            },
            {
                "x": 947.9976619057651,
                "y": 614.2001920240659
            },
            {
                "x": 949.6254698031056,
                "y": 607.1463578022571
            },
            {
                "x": 951.434145244595,
                "y": 597.1986428740652
            },
            {
                "x": 954.1471584068292,
                "y": 585.9848551368308
            },
            {
                "x": 953.9662908626802,
                "y": 579.2927560033197
            },
            {
                "x": 953.9662908626802,
                "y": 573.5049945905537
            },
            {
                "x": 954.6897610392759,
                "y": 557.2269156171486
            },
            {
                "x": 955.5940987600206,
                "y": 551.2582866602336
            },
            {
                "x": 955.7749663041697,
                "y": 545.8322603357651
            },
            {
                "x": 956.6793040249144,
                "y": 539.3210287464033
            },
            {
                "x": 958.8497145547018,
                "y": 537.6932208490626
            },
            {
                "x": 959.5731847312975,
                "y": 542.0340419086374
            },
            {
                "x": 959.5731847312975,
                "y": 550.5348164836378
            },
            {
                "x": 958.8497145547018,
                "y": 560.3016638676808
            },
            {
                "x": 958.8497145547018,
                "y": 570.6111138841705
            },
            {
                "x": 958.4879794664037,
                "y": 581.1014314448092
            },
            {
                "x": 958.4879794664037,
                "y": 590.3256761964053
            },
            {
                "x": 958.8497145547018,
                "y": 601.1777288453419
            },
            {
                "x": 958.4879794664037,
                "y": 608.5932981554487
            },
            {
                "x": 956.1367013924674,
                "y": 616.3706025538531
            },
            {
                "x": 954.1471584068292,
                "y": 624.5096420405556
            },
            {
                "x": 952.5193505094887,
                "y": 632.4678139831093
            },
            {
                "x": 951.795880332893,
                "y": 639.1599131166201
            },
            {
                "x": 949.6254698031056,
                "y": 648.7458929565141
            },
            {
                "x": 947.4550592733183,
                "y": 659.055342973004
            },
            {
                "x": 945.8272513759778,
                "y": 666.8326473714085
            },
            {
                "x": 944.380311022786,
                "y": 677.1420973878984
            },
            {
                "x": 942.5716355812967,
                "y": 684.738534242154
            },
            {
                "x": 940.4012250515093,
                "y": 693.2393088171543
            },
            {
                "x": 939.3160197866159,
                "y": 703.548758833644
            },
            {
                "x": 938.411682065871,
                "y": 708.9747851581125
            },
            {
                "x": 937.8690794334242,
                "y": 714.0390763942827
            },
            {
                "x": 937.6882118892754,
                "y": 718.3798974538573
            },
            {
                "x": 937.6882118892754,
                "y": 720
            }
        ],
        "rectMask": {
            "xMin": 927.3787618727855,
            "yMin": 537.6932208490626,
            "width": 32.19442285851197,
            "height": 182.30677915093722
        },
        "labels": {
            "labelName": "unnamed",
            "labelColor": "red",
            "labelColorRGB": "255,0,0",
            "visibility": false
        },
        "labelLocation": {
            "x": 943.4759733020414,
            "y": 628.8466104245313
        },
        "contentType": "polygon"
    },
    {
        "content": [
            {
                "x": 624.9682280557518,
                "y": 324.9929889299051
            },
            {
                "x": 627.6812412179859,
                "y": 320.1095652378836
            },
            {
                "x": 631.4794596451137,
                "y": 314.86440645756426
            },
            {
                "x": 637.8098236903268,
                "y": 311.0661880304364
            },
            {
                "x": 644.3210552796887,
                "y": 305.6401617059681
            },
            {
                "x": 649.2044789717102,
                "y": 300.75673801394663
            },
            {
                "x": 654.2687702078806,
                "y": 294.7881090570315
            },
            {
                "x": 658.4287237233063,
                "y": 287.19167220277586
            },
            {
                "x": 662.4078096945831,
                "y": 280.13783798096705
            },
            {
                "x": 665.1208228568172,
                "y": 273.44573884745614
            },
            {
                "x": 665.4825579451151,
                "y": 268.2005800671368
            },
            {
                "x": 666.7486307541577,
                "y": 264.22149409586
            },
            {
                "x": 667.6529684749024,
                "y": 260.0615405804343
            },
            {
                "x": 667.8338360190514,
                "y": 252.46510372617865
            },
            {
                "x": 668.1955711073492,
                "y": 245.23040196022097
            },
            {
                "x": 668.3764386514982,
                "y": 236.00615720862484
            },
            {
                "x": 667.6529684749024,
                "y": 228.95232298681603
            },
            {
                "x": 667.6529684749024,
                "y": 223.16456157404983
            },
            {
                "x": 669.2807763722429,
                "y": 217.19593261713467
            },
            {
                "x": 671.6320544461792,
                "y": 217.7385352495815
            },
            {
                "x": 671.9937895344771,
                "y": 224.79236947139032
            },
            {
                "x": 673.0789947993708,
                "y": 232.75054141394384
            },
            {
                "x": 673.0789947993708,
                "y": 241.61305107724206
            },
            {
                "x": 673.0789947993708,
                "y": 250.65642828468927
            },
            {
                "x": 673.0789947993708,
                "y": 258.4337326830938
            },
            {
                "x": 672.1746570786261,
                "y": 267.11537480224314
            },
            {
                "x": 671.0894518137324,
                "y": 274.5309441123498
            },
            {
                "x": 668.7381737397961,
                "y": 281.2230432458607
            },
            {
                "x": 666.0251605775619,
                "y": 287.73427483522266
            },
            {
                "x": 660.7800017972426,
                "y": 296.23504941022304
            },
            {
                "x": 654.6305052961785,
                "y": 304.0123538086276
            },
            {
                "x": 645.9488631770294,
                "y": 311.4279231187343
            },
            {
                "x": 640.7037043967098,
                "y": 316.31134681075577
            },
            {
                "x": 634.0116052631989,
                "y": 321.3756380469262
            },
            {
                "x": 630.9368570126669,
                "y": 324.0886512091604
            },
            {
                "x": 626.9577710413901,
                "y": 325.17385647405405
            }
        ],
        "rectMask": {
            "xMin": 624.9682280557518,
            "yMin": 217.19593261713467,
            "width": 48.110766743619,
            "height": 107.97792385691933
        },
        "labels": {
            "labelName": "unnamed",
            "labelColor": "red",
            "labelColorRGB": "255,0,0",
            "visibility": false
        },
        "labelLocation": {
            "x": 649.0236114275613,
            "y": 271.1848945455943
        },
        "contentType": "polygon"
    },
    {
        "content": [
            {
                "x": 150.67680337032178,
                "y": 271.91955575407366
            },
            {
                "x": 147.24739013798202,
                "y": 270.7764180099604
            },
            {
                "x": 146.6758212659254,
                "y": 267.1564818202684
            },
            {
                "x": 151.81994111443507,
                "y": 262.7744538011676
            },
            {
                "x": 156.20196913353593,
                "y": 255.72510437913584
            },
            {
                "x": 161.34608898204556,
                "y": 250.19993861592175
            },
            {
                "x": 168.2049154467251,
                "y": 245.43686468211652
            },
            {
                "x": 173.53955825258697,
                "y": 239.9116989189024
            },
            {
                "x": 179.06472401580106,
                "y": 233.62444132627948
            },
            {
                "x": 183.25622907754968,
                "y": 228.8613673924743
            },
            {
                "x": 184.97093569371955,
                "y": 229.05189034982646
            },
            {
                "x": 185.35198160842398,
                "y": 233.4339183689273
            },
            {
                "x": 183.6372749922541,
                "y": 237.6254234306759
            },
            {
                "x": 179.25524697315328,
                "y": 242.00745144977674
            },
            {
                "x": 175.06374191140466,
                "y": 246.19895651152535
            },
            {
                "x": 169.34805319083839,
                "y": 251.72412227473944
            },
            {
                "x": 163.82288742762427,
                "y": 257.63033395265796
            },
            {
                "x": 159.25033645117122,
                "y": 262.7744538011676
            },
            {
                "x": 155.05883138942264,
                "y": 267.9185736496773
            }
        ],
        "rectMask": {
            "xMin": 146.6758212659254,
            "yMin": 228.8613673924743,
            "width": 38.67616034249858,
            "height": 43.0581883615994
        },
        "labels": {
            "labelName": "unnamed",
            "labelColor": "red",
            "labelColorRGB": "255,0,0",
            "visibility": false
        },
        "labelLocation": {
            "x": 166.0139014371747,
            "y": 250.390461573274
        },
        "contentType": "polygon"
    },
    {
        "content": [
            {
                "x": 126.40166198393327,
                "y": 487.1036186844971
            },
            {
                "x": 133.6099710442201,
                "y": 483.4994641543537
            },
            {
                "x": 138.31104217049412,
                "y": 480.0520119950861
            },
            {
                "x": 143.32551803851976,
                "y": 476.2911550940669
            },
            {
                "x": 146.77297019778737,
                "y": 470.80657211341384
            },
            {
                "x": 149.1235057609244,
                "y": 462.814751198748
            },
            {
                "x": 149.43691050267597,
                "y": 456.7033587345918
            },
            {
                "x": 150.5338270988066,
                "y": 449.49504967430494
            },
            {
                "x": 150.37712472793078,
                "y": 445.26408566065834
            },
            {
                "x": 151.9441484366888,
                "y": 438.6825860838747
            },
            {
                "x": 152.7276602910678,
                "y": 433.98151495760067
            },
            {
                "x": 155.0781958542048,
                "y": 429.750550943954
            },
            {
                "x": 157.5854337882176,
                "y": 425.6762893011832
            },
            {
                "x": 161.18958831836105,
                "y": 420.03500394965437
            },
            {
                "x": 165.42055233200767,
                "y": 415.647337565132
            },
            {
                "x": 168.8680044912753,
                "y": 413.92361148549816
            },
            {
                "x": 176.85982540594114,
                "y": 410.6328616971063
            },
            {
                "x": 185.79186054586177,
                "y": 405.7750881999565
            },
            {
                "x": 189.8661221886326,
                "y": 403.4245526368195
            },
            {
                "x": 197.07443124891944,
                "y": 400.2905052193035
            },
            {
                "x": 200.20847866643544,
                "y": 400.2905052193035
            },
            {
                "x": 202.71571660044827,
                "y": 400.6039099610551
            },
            {
                "x": 208.82710906460449,
                "y": 401.7008265571857
            },
            {
                "x": 213.84158493263013,
                "y": 401.7008265571857
            },
            {
                "x": 218.22925131715255,
                "y": 405.4616834582049
            },
            {
                "x": 222.93032244342658,
                "y": 408.2823261339693
            },
            {
                "x": 229.0417149075828,
                "y": 412.3565877767401
            },
            {
                "x": 234.05619077560843,
                "y": 415.80403993600777
            },
            {
                "x": 238.91396427275825,
                "y": 420.03500394965437
            },
            {
                "x": 244.39854725341127,
                "y": 424.5793727050526
            },
            {
                "x": 249.0996183796853,
                "y": 428.02682486432025
            },
            {
                "x": 256.62133218172374,
                "y": 431.16087228183625
            },
            {
                "x": 261.47910567887357,
                "y": 432.10108650709105
            },
            {
                "x": 265.5533673216444,
                "y": 432.7278959905943
            },
            {
                "x": 274.0152953489376,
                "y": 434.13821732847646
            },
            {
                "x": 283.1040328597341,
                "y": 436.9588600042409
            },
            {
                "x": 288.1185087277597,
                "y": 438.21247897124726
            },
            {
                "x": 293.91649645016435,
                "y": 440.0929074217569
            },
            {
                "x": 300.497996026948,
                "y": 441.9733358722665
            },
            {
                "x": 307.8630074581106,
                "y": 443.0702524683971
            },
            {
                "x": 317.7352568232861,
                "y": 446.36100225678894
            },
            {
                "x": 323.0631374330633,
                "y": 448.55483544905013
            },
            {
                "x": 327.7642085593373,
                "y": 451.8455852374419
            },
            {
                "x": 333.7188986526177,
                "y": 453.8827160588274
            },
            {
                "x": 341.39731482553196,
                "y": 459.3672990394804
            },
            {
                "x": 347.50870728968823,
                "y": 465.47869150363664
            },
            {
                "x": 353.14999264121707,
                "y": 471.59008396779285
            },
            {
                "x": 356.28404005873307,
                "y": 475.0375361270605
            },
            {
                "x": 360.2015993306281,
                "y": 479.2685001407071
            },
            {
                "x": 364.2758609733989,
                "y": 483.4994641543537
            },
            {
                "x": 369.1336344705487,
                "y": 487.57372579712455
            },
            {
                "x": 373.36459848419537,
                "y": 490.39436847288897
            },
            {
                "x": 377.2821577560904,
                "y": 492.74490403602596
            },
            {
                "x": 380.5729075444822,
                "y": 494.1552253739082
            },
            {
                "x": 385.74408578338364,
                "y": 495.5655467117904
            },
            {
                "x": 390.13175216790603,
                "y": 496.97586804967256
            },
            {
                "x": 394.67612092330427,
                "y": 498.0727846458032
            },
            {
                "x": 398.12357308257185,
                "y": 499.3264036128096
            },
            {
                "x": 402.6679418379701,
                "y": 500.2666178380644
            },
            {
                "x": 408.3092271894989,
                "y": 502.4604510303256
            },
            {
                "x": 413.6371077992762,
                "y": 504.3408794808352
            },
            {
                "x": 418.8082860381776,
                "y": 506.3780103022206
            },
            {
                "x": 424.762976131458,
                "y": 509.04195060710924
            },
            {
                "x": 430.56096385386263,
                "y": 514.2131288460107
            },
            {
                "x": 434.6352254966335,
                "y": 517.6605810052783
            },
            {
                "x": 439.8064037355349,
                "y": 522.6750568733039
            },
            {
                "x": 443.7239630074299,
                "y": 526.9060208869505
            },
            {
                "x": 451.71578392209574,
                "y": 533.4875204637342
            },
            {
                "x": 458.1405811280036,
                "y": 536.3081631394986
            },
            {
                "x": 462.0581403998986,
                "y": 539.128805815263
            },
            {
                "x": 469.42315183106126,
                "y": 542.1061508619032
            },
            {
                "x": 475.2211395534659,
                "y": 544.7700911667919
            },
            {
                "x": 483.9964723225107,
                "y": 549.0010551804385
            },
            {
                "x": 487.75732922352995,
                "y": 553.2320191940851
            },
            {
                "x": 494.80893591294097,
                "y": 558.089792691235
            },
            {
                "x": 500.1368165227182,
                "y": 564.2011851553912
            },
            {
                "x": 503.74097105286165,
                "y": 567.9620420564104
            },
            {
                "x": 507.03172084125345,
                "y": 572.0363036991812
            },
            {
                "x": 512.3596014510307,
                "y": 577.3641843089584
            },
            {
                "x": 515.9637559811741,
                "y": 580.6549340973502
            },
            {
                "x": 521.2916365909513,
                "y": 585.3560052236243
            },
            {
                "x": 523.1720650414609,
                "y": 588.1766478993886
            },
            {
                "x": 526.4628148298527,
                "y": 591.7808024295321
            },
            {
                "x": 529.7535646182446,
                "y": 595.5416593305513
            },
            {
                "x": 532.4175049231332,
                "y": 599.4592186024463
            },
            {
                "x": 535.708254711525,
                "y": 602.7499683908381
            },
            {
                "x": 542.7598614009361,
                "y": 607.2943371462363
            },
            {
                "x": 548.4011467524649,
                "y": 610.5850869346282
            },
            {
                "x": 554.0424321039937,
                "y": 611.5253011598829
            },
            {
                "x": 559.6837174555225,
                "y": 611.2118964181313
            },
            {
                "x": 565.4817051779271,
                "y": 611.0551940472556
            },
            {
                "x": 570.6528834168286,
                "y": 611.2118964181313
            },
            {
                "x": 575.6673592848542,
                "y": 612.4655153851378
            },
            {
                "x": 583.3457754577685,
                "y": 614.0325390938958
            },
            {
                "x": 590.2406797763036,
                "y": 612.6222177560136
            },
            {
                "x": 596.5087746113358,
                "y": 611.2118964181313
            },
            {
                "x": 602.9335718172435,
                "y": 608.8613608549944
            },
            {
                "x": 610.9253927319094,
                "y": 606.04071817923
            },
            {
                "x": 615.7831662290592,
                "y": 606.9809324044847
            },
            {
                "x": 620.0141302427058,
                "y": 610.5850869346282
            },
            {
                "x": 627.0657369321169,
                "y": 616.6964793987844
            },
            {
                "x": 631.1399985748877,
                "y": 621.5542528959343
            },
            {
                "x": 637.2513910390439,
                "y": 628.1357524727179
            },
            {
                "x": 641.9524621653179,
                "y": 633.1502283407435
            },
            {
                "x": 649.1607712256048,
                "y": 638.7915136922724
            },
            {
                "x": 651.8247115304933,
                "y": 643.6492871894222
            },
            {
                "x": 653.705139981003,
                "y": 647.8802512030688
            },
            {
                "x": 656.0556755441401,
                "y": 653.5215365545977
            },
            {
                "x": 658.8763182199044,
                "y": 659.0061195352507
            },
            {
                "x": 661.8536632665447,
                "y": 664.6474048867796
            },
            {
                "x": 664.0474964588059,
                "y": 667.1546428207923
            },
            {
                "x": 668.2784604724525,
                "y": 669.9752854965568
            },
            {
                "x": 672.1960197443475,
                "y": 674.0495471393276
            },
            {
                "x": 675.016662420112,
                "y": 677.3402969277194
            },
            {
                "x": 679.2476264337586,
                "y": 681.2578561996144
            },
            {
                "x": 682.5383762221503,
                "y": 686.27233206764
            },
            {
                "x": 685.8291260105422,
                "y": 692.0703197900447
            },
            {
                "x": 687.552852090176,
                "y": 696.3012838036913
            },
            {
                "x": 689.119875798934,
                "y": 700.0621407047105
            },
            {
                "x": 692.2539232164501,
                "y": 705.233318943612
            },
            {
                "x": 693.820946925208,
                "y": 708.367366361128
            },
            {
                "x": 694.2910540378355,
                "y": 710.717901924265
            },
            {
                "x": 695.0745658922144,
                "y": 715.1055683087874
            },
            {
                "x": 696.0147801174693,
                "y": 717.9262109845519
            },
            {
                "x": 698.3653156806063,
                "y": 719.336532322434
            },
            {
                "x": 698.3653156806063,
                "y": 715.8890801631663
            },
            {
                "x": 697.5818038262272,
                "y": 711.6581161495197
            },
            {
                "x": 696.1714824883451,
                "y": 707.5838545067489
            },
            {
                "x": 693.1941374417048,
                "y": 700.5322478173379
            },
            {
                "x": 691.9405184746984,
                "y": 696.7713909163188
            },
            {
                "x": 688.9631734280582,
                "y": 691.4435103065415
            },
            {
                "x": 685.3590188979148,
                "y": 685.3321178423853
            },
            {
                "x": 682.3816738512745,
                "y": 680.787749086987
            },
            {
                "x": 679.2476264337586,
                "y": 676.4000827024646
            },
            {
                "x": 675.8001742744909,
                "y": 671.6990115761905
            },
            {
                "x": 669.8454841812105,
                "y": 666.5278333372892
            },
            {
                "x": 666.5547343928187,
                "y": 662.7669764362699
            },
            {
                "x": 664.2041988296817,
                "y": 660.1030361313813
            },
            {
                "x": 661.6969608956689,
                "y": 656.1854768594862
            },
            {
                "x": 659.3464253325318,
                "y": 651.9545128458396
            },
            {
                "x": 657.1525921402706,
                "y": 647.723548832193
            },
            {
                "x": 655.5855684315126,
                "y": 643.022477705919
            },
            {
                "x": 652.4515210139966,
                "y": 638.3214065796449
            },
            {
                "x": 649.6308783382322,
                "y": 635.0306567912531
            },
            {
                "x": 646.3401285498404,
                "y": 631.4265022611097
            },
            {
                "x": 642.8926763905728,
                "y": 628.4491572144694
            },
            {
                "x": 640.5421408274358,
                "y": 626.0986216513325
            },
            {
                "x": 637.4080934099197,
                "y": 622.3377647503132
            },
            {
                "x": 632.2369151710183,
                "y": 618.2635031075424
            },
            {
                "x": 629.8863796078813,
                "y": 615.442860431778
            },
            {
                "x": 626.909034561241,
                "y": 612.4655153851378
            },
            {
                "x": 623.6182847728493,
                "y": 609.3314679676217
            },
            {
                "x": 620.0141302427058,
                "y": 606.824230033609
            },
            {
                "x": 617.9769994213204,
                "y": 605.5706110666025
            },
            {
                "x": 614.6862496329286,
                "y": 603.6901826160929
            },
            {
                "x": 610.455285619282,
                "y": 603.0633731325897
            },
            {
                "x": 602.620167075492,
                "y": 605.8840158083542
            },
            {
                "x": 596.35207224046,
                "y": 607.7644442588637
            },
            {
                "x": 592.5912153394407,
                "y": 608.7046584841186
            },
            {
                "x": 587.4200371005393,
                "y": 610.2716821928766
            },
            {
                "x": 580.0550256693766,
                "y": 610.741789305504
            },
            {
                "x": 573.473526092593,
                "y": 609.1747655967459
            },
            {
                "x": 566.2652170323062,
                "y": 608.7046584841186
            },
            {
                "x": 560.6239316807773,
                "y": 608.2345513714912
            },
            {
                "x": 554.1991344748695,
                "y": 608.391253742367
            },
            {
                "x": 548.4011467524649,
                "y": 607.9211466297396
            },
            {
                "x": 545.1103969640731,
                "y": 605.4139086957267
            },
            {
                "x": 538.6855997581653,
                "y": 601.3396470529559
            },
            {
                "x": 535.8649570824008,
                "y": 597.5787901519367
            },
            {
                "x": 532.4175049231332,
                "y": 594.131337992669
            },
            {
                "x": 528.6566480221139,
                "y": 589.1168621246435
            },
            {
                "x": 526.3061124589769,
                "y": 585.8261123362516
            },
            {
                "x": 521.7617437035788,
                "y": 581.9085530643566
            },
            {
                "x": 518.4709939151869,
                "y": 577.8342914215858
            },
            {
                "x": 514.7101370141677,
                "y": 574.8569463749456
            },
            {
                "x": 509.22555403351464,
                "y": 570.7826847321747
            },
            {
                "x": 506.4049113577502,
                "y": 567.3352325729071
            },
            {
                "x": 501.86054260235204,
                "y": 563.2609709301363
            },
            {
                "x": 499.3533046683392,
                "y": 559.0300069164897
            },
            {
                "x": 497.0027691052022,
                "y": 556.2093642407253
            },
            {
                "x": 492.3016979789282,
                "y": 551.9784002270786
            },
            {
                "x": 485.4067936603929,
                "y": 547.1206267299289
            },
            {
                "x": 481.0191272758705,
                "y": 544.2999840541644
            },
            {
                "x": 474.59433006996267,
                "y": 541.1659366366484
            },
            {
                "x": 470.83347316894344,
                "y": 538.6586987026355
            },
            {
                "x": 465.50559255916625,
                "y": 536.4648655103744
            },
            {
                "x": 461.4313309163954,
                "y": 533.4875204637342
            },
            {
                "x": 457.51377164450037,
                "y": 532.077199125852
            },
            {
                "x": 452.81270051822634,
                "y": 529.2565564500876
            },
            {
                "x": 447.64152227932493,
                "y": 526.4359137743231
            },
            {
                "x": 441.2167250734171,
                "y": 520.4812236810427
            },
            {
                "x": 437.45586817239786,
                "y": 516.5636644091477
            },
            {
                "x": 433.22490415875126,
                "y": 512.3327003955011
            },
            {
                "x": 429.93415437035947,
                "y": 509.5120577197367
            },
            {
                "x": 425.7031903567128,
                "y": 505.90790318959324
            },
            {
                "x": 421.7856310848178,
                "y": 503.5573676264562
            },
            {
                "x": 417.08455995854376,
                "y": 501.5202368050708
            },
            {
                "x": 411.4432746070149,
                "y": 499.796510725437
            },
            {
                "x": 406.89890585161675,
                "y": 498.3861893875548
            },
            {
                "x": 402.6679418379701,
                "y": 497.4459751623
            },
            {
                "x": 398.4369778243235,
                "y": 495.87895145354196
            },
            {
                "x": 394.98952566505585,
                "y": 494.93873722828715
            },
            {
                "x": 390.2884545387818,
                "y": 493.528415890405
            },
            {
                "x": 378.69247909397257,
                "y": 489.76755898938575
            },
            {
                "x": 373.05119374244373,
                "y": 486.47680920099396
            },
            {
                "x": 368.82022972879713,
                "y": 483.1860594126021
            },
            {
                "x": 365.0593728277779,
                "y": 479.5819048824587
            },
            {
                "x": 358.47787325099426,
                "y": 473.47051241830246
            },
            {
                "x": 354.87371872085083,
                "y": 469.23954840465586
            },
            {
                "x": 350.48605233632844,
                "y": 464.0683701657544
            },
            {
                "x": 347.35200491881244,
                "y": 460.7776203773626
            },
            {
                "x": 342.180826679911,
                "y": 455.60644213846115
            },
            {
                "x": 338.7333745206434,
                "y": 452.78579946269673
            },
            {
                "x": 336.06943421575477,
                "y": 450.43526389955974
            },
            {
                "x": 330.42814886422593,
                "y": 447.9280259655469
            },
            {
                "x": 324.7868635126971,
                "y": 445.26408566065834
            },
            {
                "x": 318.20536393591345,
                "y": 443.3836572101487
            },
            {
                "x": 311.93726910088145,
                "y": 440.8764192761359
            },
            {
                "x": 306.76609086198,
                "y": 438.9959908256263
            },
            {
                "x": 296.580436755053,
                "y": 437.27226474599246
            },
            {
                "x": 288.90202058213873,
                "y": 434.9217291828555
            },
            {
                "x": 281.85041389272766,
                "y": 433.35470547409744
            },
            {
                "x": 275.42561668681986,
                "y": 431.94438413621526
            },
            {
                "x": 269.78433133529103,
                "y": 430.06395568570565
            },
            {
                "x": 263.0461293876316,
                "y": 428.8103367186992
            },
            {
                "x": 256.46462981084795,
                "y": 427.8701224934444
            },
            {
                "x": 253.17388002245613,
                "y": 426.3030987846864
            },
            {
                "x": 248.0027017835547,
                "y": 423.1690513671704
            },
            {
                "x": 246.1222733330451,
                "y": 421.6020276584124
            },
            {
                "x": 239.69747612713726,
                "y": 416.7442541612626
            },
            {
                "x": 235.15310737173903,
                "y": 412.82669488936756
            },
            {
                "x": 231.235548099844,
                "y": 409.6926474718515
            },
            {
                "x": 225.2808580065636,
                "y": 407.1854095378387
            },
            {
                "x": 220.42308450941374,
                "y": 402.95444552419207
            },
            {
                "x": 216.66222760839455,
                "y": 401.0740170736825
            },
            {
                "x": 212.90137070737532,
                "y": 398.88018388142126
            },
            {
                "x": 207.88689483934968,
                "y": 397.78326728529066
            },
            {
                "x": 203.02912134219986,
                "y": 397.4698625435391
            },
            {
                "x": 198.01464547417424,
                "y": 397.93996965616645
            },
            {
                "x": 194.09708620227923,
                "y": 399.6636957358003
            },
            {
                "x": 190.8063364138874,
                "y": 400.1338028484277
            },
            {
                "x": 186.10526528761338,
                "y": 401.2307194445583
            },
            {
                "x": 181.56089653221514,
                "y": 404.3647668620743
            },
            {
                "x": 177.64333726032012,
                "y": 406.2451953125839
            },
            {
                "x": 173.8824803593009,
                "y": 408.5957308757209
            },
            {
                "x": 167.92779026602048,
                "y": 411.10296880973374
            },
            {
                "x": 164.01023099412546,
                "y": 412.98339726024335
            },
            {
                "x": 161.18958831836105,
                "y": 415.33393282338034
            },
            {
                "x": 156.0184100794596,
                "y": 420.8185158040334
            },
            {
                "x": 153.6678745163226,
                "y": 425.04947981768004
            },
            {
                "x": 151.787446065813,
                "y": 428.4969319769476
            },
            {
                "x": 150.84723184055818,
                "y": 432.25778887796685
            },
            {
                "x": 148.96680339004857,
                "y": 436.48875289161344
            },
            {
                "x": 147.71318442304218,
                "y": 441.0331216470117
            },
            {
                "x": 147.5564820521664,
                "y": 444.7939785480309
            },
            {
                "x": 147.71318442304218,
                "y": 449.02494256167756
            },
            {
                "x": 147.71318442304218,
                "y": 452.47239472094515
            },
            {
                "x": 147.08637493953898,
                "y": 456.0765492510886
            },
            {
                "x": 146.30286308515997,
                "y": 459.8374061521078
            },
            {
                "x": 145.36264885990516,
                "y": 462.814751198748
            },
            {
                "x": 144.73583937640197,
                "y": 466.57560809976724
            },
            {
                "x": 143.48222040939555,
                "y": 470.33646500078646
            },
            {
                "x": 140.66157773363113,
                "y": 474.41072664355727
            },
            {
                "x": 138.62444691224573,
                "y": 477.3880716901975
            },
            {
                "x": 134.0800781568475,
                "y": 478.7983930280797
            },
            {
                "x": 130.16251888495248,
                "y": 481.9324404455957
            },
            {
                "x": 126.08825724218167,
                "y": 484.2829760087327
            }
        ],
        "rectMask": {
            "xMin": 126.08825724218167,
            "yMin": 397.4698625435391,
            "width": 572.2770584384245,
            "height": 321.86666977889496
        },
        "labels": {
            "labelName": "unnamed",
            "labelColor": "red",
            "labelColorRGB": "255,0,0",
            "visibility": false
        },
        "labelLocation": {
            "x": 412.22678646139394,
            "y": 558.4031974329865
        },
        "contentType": "polygon"
    }
]