[
    {
        "content": [
            {
                "x": 1041.7188380021155,
                "y": 304.83214648637124
            },
            {
                "x": 1034.4252394122902,
                "y": 299.7583387717103
            },
            {
                "x": 1026.814527840299,
                "y": 293.5746356194673
            },
            {
                "x": 1015.0813475001457,
                "y": 289.135053869139
            },
            {
                "x": 1006.9949664549048,
                "y": 283.902689663395
            },
            {
                "x": 996.3716815523335,
                "y": 278.8288819487341
            },
            {
                "x": 987.8096310338432,
                "y": 273.59651774299
            },
            {
                "x": 988.4438569981759,
                "y": 270.58394441241006
            },
            {
                "x": 994.6275601504187,
                "y": 272.9622917786574
            },
            {
                "x": 1001.2869327759113,
                "y": 275.9748651092373
            },
            {
                "x": 1008.8976443479027,
                "y": 280.2558903684824
            },
            {
                "x": 1016.8254689020603,
                "y": 284.5369156277276
            },
            {
                "x": 1024.1190674918853,
                "y": 288.1837149226401
            },
            {
                "x": 1035.3765783587892,
                "y": 294.84308754813253
            },
            {
                "x": 1042.6701769486142,
                "y": 298.8069998252114
            },
            {
                "x": 1052.659235886853,
                "y": 303.8808075398723
            },
            {
                "x": 1062.014068860759,
                "y": 309.5888412188658
            },
            {
                "x": 1068.8319979773346,
                "y": 314.979761915693
            },
            {
                "x": 1078.8210569155733,
                "y": 320.5292391036034
            },
            {
                "x": 1082.626412701569,
                "y": 323.5418124341834
            },
            {
                "x": 1088.810115853812,
                "y": 329.24984611317683
            },
            {
                "x": 1094.3595930417223,
                "y": 333.0552018991725
            },
            {
                "x": 1100.226183211799,
                "y": 335.90921873866927
            },
            {
                "x": 1107.361225310541,
                "y": 338.12900961383343
            },
            {
                "x": 1110.532355132204,
                "y": 339.55601803358184
            },
            {
                "x": 1109.7395726767882,
                "y": 342.4100348730786
            },
            {
                "x": 1105.458547417543,
                "y": 343.3613738195775
            },
            {
                "x": 1097.8478358455516,
                "y": 340.0316875068313
            },
            {
                "x": 1090.2371242735603,
                "y": 334.9578797921704
            },
            {
                "x": 1080.0895088442385,
                "y": 327.66428120234525
            },
            {
                "x": 1074.381475165245,
                "y": 323.5418124341834
            },
            {
                "x": 1066.9293200843367,
                "y": 318.62656121060553
            },
            {
                "x": 1059.6357214945117,
                "y": 313.55275349594467
            },
            {
                "x": 1052.5006793957698,
                "y": 309.747397709949
            },
            {
                "x": 1048.8538801008574,
                "y": 308.16183279911746
            }
        ],
        "rectMask": {
            "xMin": 987.8096310338432,
            "yMin": 270.58394441241006,
            "width": 122.72272409836073,
            "height": 72.77742940716742
        },
        "labels": {
            "labelName": "unnamed",
            "labelColor": "red",
            "labelColorRGB": "255,0,0",
            "visibility": false
        },
        "labelLocation": {
            "x": 1049.1709930830236,
            "y": 306.9726591159938
        },
        "contentType": "polygon"
    },
    {
        "content": [
            {
                "x": 817.5199596105366,
                "y": 360.96114432980755
            },
            {
                "x": 820.3739764500331,
                "y": 360.8025878387244
            },
            {
                "x": 824.1793322360289,
                "y": 359.8512488922254
            },
            {
                "x": 827.9846880220244,
                "y": 358.5827969635602
            },
            {
                "x": 830.0459224061055,
                "y": 356.0458931062297
            },
            {
                "x": 832.7413827545192,
                "y": 353.3504327578162
            },
            {
                "x": 836.5467385405149,
                "y": 350.97208539156884
            },
            {
                "x": 837.1809645048475,
                "y": 353.8261022310656
            },
            {
                "x": 834.644060647517,
                "y": 356.5215625794792
            },
            {
                "x": 832.4242697723529,
                "y": 359.0584664368097
            },
            {
                "x": 828.1432445131079,
                "y": 360.96114432980755
            },
            {
                "x": 824.6550017092784,
                "y": 362.3881527495559
            },
            {
                "x": 821.4838718876154,
                "y": 363.33949169605484
            },
            {
                "x": 815.1416122442893,
                "y": 364.76650011580324
            },
            {
                "x": 810.3849175117946,
                "y": 366.1935085355516
            },
            {
                "x": 805.3111097971336,
                "y": 367.6205169553
            },
            {
                "x": 802.2985364665539,
                "y": 368.0961864285494
            },
            {
                "x": 804.6768838328012,
                "y": 365.7178390623021
            },
            {
                "x": 808.4822396187967,
                "y": 363.6566046782212
            },
            {
                "x": 811.4948129493766,
                "y": 362.7052657317222
            },
            {
                "x": 814.8244992621229,
                "y": 361.75392678522326
            }
        ],
        "rectMask": {
            "xMin": 802.2985364665539,
            "yMin": 350.97208539156884,
            "width": 34.882428038293746,
            "height": 17.124101036980566
        },
        "labels": {
            "labelName": "unnamed",
            "labelColor": "red",
            "labelColorRGB": "255,0,0",
            "visibility": false
        },
        "labelLocation": {
            "x": 819.7397504857007,
            "y": 359.53413591005915
        },
        "contentType": "polygon"
    },
    {
        "content": [
            {
                "x": 20.930618222049183,
                "y": 325.92793217744446
            },
            {
                "x": 20.930618222049183,
                "y": 323.59621907328045
            },
            {
                "x": 16.578087094276345,
                "y": 322.81898137189245
            },
            {
                "x": 13.469136288724318,
                "y": 321.419953509394
            },
            {
                "x": 13.002793667891515,
                "y": 319.865478106618
            },
            {
                "x": 13.935478909557123,
                "y": 316.756527301066
            },
            {
                "x": 15.179059231777934,
                "y": 314.73570927745715
            },
            {
                "x": 18.443457577607564,
                "y": 312.0931010927379
            },
            {
                "x": 21.863303463714793,
                "y": 310.5386256899619
            },
            {
                "x": 24.195016567878813,
                "y": 312.5594437135707
            },
            {
                "x": 26.526729672042833,
                "y": 314.73570927745715
            },
            {
                "x": 29.169337856762056,
                "y": 316.29018468023315
            },
            {
                "x": 30.102023098427665,
                "y": 315.20205189828994
            },
            {
                "x": 28.702995235929254,
                "y": 312.8703387941259
            },
            {
                "x": 26.37128213176523,
                "y": 311.47131093162756
            },
            {
                "x": 23.106883785935604,
                "y": 309.2950453677411
            },
            {
                "x": 21.70785592343719,
                "y": 308.3623601260755
            },
            {
                "x": 19.531590359550773,
                "y": 308.82870274690833
            },
            {
                "x": 16.578087094276345,
                "y": 311.0049683107947
            },
            {
                "x": 13.469136288724318,
                "y": 312.8703387941259
            },
            {
                "x": 10.515633023449892,
                "y": 315.82384205940036
            },
            {
                "x": 9.272052701229082,
                "y": 318.1555551635644
            },
            {
                "x": 9.11660516095148,
                "y": 321.26450596911644
            },
            {
                "x": 10.049290402617089,
                "y": 323.59621907328045
            },
            {
                "x": 12.38100350678111,
                "y": 324.2180092343908
            },
            {
                "x": 14.86816415122273,
                "y": 324.9952469357788
            },
            {
                "x": 17.510772335941954,
                "y": 325.61703709688925
            },
            {
                "x": 19.37614281927317,
                "y": 325.92793217744446
            }
        ],
        "rectMask": {
            "xMin": 9.11660516095148,
            "yMin": 308.3623601260755,
            "width": 20.985417937476186,
            "height": 17.565572051368957
        },
        "labels": {
            "labelName": "unnamed",
            "labelColor": "red",
            "labelColorRGB": "255,0,0",
            "visibility": false
        },
        "labelLocation": {
            "x": 19.609314129689572,
            "y": 317.14514615175995
        },
        "contentType": "polygon"
    }
]