[
    {
        "content": [
            {
                "x": 357.96799262799783,
                "y": 373.66760222874325
            },
            {
                "x": 364.4015173875914,
                "y": 374.98729961532655
            },
            {
                "x": 370.835042147185,
                "y": 376.30699700190985
            },
            {
                "x": 378.2583399467161,
                "y": 378.6164674284306
            },
            {
                "x": 384.03201601301805,
                "y": 380.92593785495137
            },
            {
                "x": 391.620275985872,
                "y": 384.22518132140965
            },
            {
                "x": 399.3734981320489,
                "y": 387.8543491345137
            },
            {
                "x": 403.9924389850905,
                "y": 389.174046521097
            },
            {
                "x": 406.79679593158,
                "y": 391.48351694761783
            },
            {
                "x": 409.4361907047466,
                "y": 393.7929873741386
            },
            {
                "x": 413.72520721114233,
                "y": 395.77253345401357
            },
            {
                "x": 418.179185890861,
                "y": 396.76230649395103
            },
            {
                "x": 424.1178241304858,
                "y": 397.7520795338885
            },
            {
                "x": 430.2214245434336,
                "y": 398.08200388053433
            },
            {
                "x": 438.6344953829022,
                "y": 398.08200388053433
            },
            {
                "x": 445.89283100911035,
                "y": 397.09223084059687
            },
            {
                "x": 451.9964314220581,
                "y": 395.9374956273365
            },
            {
                "x": 456.45041010177675,
                "y": 394.94772258739897
            },
            {
                "x": 460.24454008820373,
                "y": 392.80321433420113
            },
            {
                "x": 463.70874572798493,
                "y": 390.16381956103453
            },
            {
                "x": 466.51310267447445,
                "y": 387.8543491345137
            },
            {
                "x": 470.30723266090143,
                "y": 383.56533262811803
            },
            {
                "x": 472.4517409140993,
                "y": 381.2558622015972
            },
            {
                "x": 474.43128699397425,
                "y": 377.1318078685244
            },
            {
                "x": 477.07068176714085,
                "y": 372.34790484215995
            },
            {
                "x": 479.0502278470158,
                "y": 371.35813180222243
            },
            {
                "x": 479.2151900203387,
                "y": 373.66760222874325
            },
            {
                "x": 477.5655682871096,
                "y": 378.6164674284306
            },
            {
                "x": 474.7612113406201,
                "y": 382.5755595881805
            },
            {
                "x": 472.6167030874222,
                "y": 385.54487870799295
            },
            {
                "x": 467.66783788773483,
                "y": 390.82366825432615
            },
            {
                "x": 463.87370790130785,
                "y": 393.13313868084697
            },
            {
                "x": 458.42995618165173,
                "y": 396.4323821473052
            },
            {
                "x": 453.64605315528723,
                "y": 398.41192822718017
            },
            {
                "x": 447.70741491566235,
                "y": 399.40170126711763
            },
            {
                "x": 443.08847406262083,
                "y": 399.73162561376347
            },
            {
                "x": 436.4899871297043,
                "y": 400.3914743070551
            },
            {
                "x": 430.0564623701107,
                "y": 400.88636082702385
            },
            {
                "x": 424.7776728237775,
                "y": 400.88636082702385
            },
            {
                "x": 417.0244506776006,
                "y": 399.73162561376347
            },
            {
                "x": 413.2303206911736,
                "y": 399.0717769204718
            },
            {
                "x": 407.45664462487167,
                "y": 396.26741997398227
            },
            {
                "x": 403.9924389850905,
                "y": 394.12291172078443
            },
            {
                "x": 401.5180063852468,
                "y": 391.48351694761783
            },
            {
                "x": 395.90929249226775,
                "y": 389.33900869441993
            },
            {
                "x": 390.46554077261163,
                "y": 386.3696895746075
            },
            {
                "x": 386.1765242662159,
                "y": 384.06021914808673
            },
            {
                "x": 378.2583399467161,
                "y": 382.4105974148576
            },
            {
                "x": 374.2992477869662,
                "y": 380.92593785495137
            },
            {
                "x": 369.84526910724753,
                "y": 379.2763161217223
            },
            {
                "x": 365.88617694749763,
                "y": 377.956618735139
            },
            {
                "x": 362.9168578276852,
                "y": 377.2967700418473
            },
            {
                "x": 359.28769001458113,
                "y": 376.47195917523277
            },
            {
                "x": 357.47310610802907,
                "y": 375.48218613529525
            }
        ],
        "rectMask": {
            "xMin": 357.47310610802907,
            "yMin": 371.35813180222243,
            "width": 121.74208391230965,
            "height": 29.52822902480139
        },
        "labels": {
            "labelName": "unnamed",
            "labelColor": "red",
            "labelColorRGB": "255,0,0",
            "visibility": false
        },
        "labelLocation": {
            "x": 418.3441480641839,
            "y": 386.1222463146231
        },
        "contentType": "polygon"
    },
    {
        "content": [
            {
                "x": 499.1756129924112,
                "y": 271.3910547685373
            },
            {
                "x": 503.9595160187756,
                "y": 272.05090346182897
            },
            {
                "x": 502.80478080551524,
                "y": 266.7721139154957
            },
            {
                "x": 497.1960669125362,
                "y": 262.9779839290687
            },
            {
                "x": 491.917277366203,
                "y": 258.52400524935007
            },
            {
                "x": 485.3187904332865,
                "y": 251.43063179646484
            },
            {
                "x": 477.5655682871096,
                "y": 246.48176659677745
            },
            {
                "x": 469.15249744764105,
                "y": 242.35771226370463
            },
            {
                "x": 464.5335565945995,
                "y": 240.5431283571526
            },
            {
                "x": 457.935069661683,
                "y": 236.08914967743397
            },
            {
                "x": 452.6562801153498,
                "y": 231.3052466510695
            },
            {
                "x": 445.5629066624645,
                "y": 225.69653275809046
            },
            {
                "x": 438.1396088629334,
                "y": 219.42797017181977
            },
            {
                "x": 434.51044104982935,
                "y": 216.12872670536152
            },
            {
                "x": 426.7572189036525,
                "y": 211.50978585231994
            },
            {
                "x": 419.6638454507672,
                "y": 208.2105423858617
            },
            {
                "x": 407.45664462487167,
                "y": 204.4164123994347
            },
            {
                "x": 395.90929249226775,
                "y": 202.60182849288265
            },
            {
                "x": 387.4962216527992,
                "y": 199.96243371971605
            },
            {
                "x": 377.76345342674733,
                "y": 197.32303894654945
            },
            {
                "x": 368.85549606731007,
                "y": 194.51868200005993
            },
            {
                "x": 363.24678217433103,
                "y": 193.36394678679954
            },
            {
                "x": 363.41174434765395,
                "y": 195.50845503999741
            },
            {
                "x": 368.52557172066423,
                "y": 197.81792546651818
            },
            {
                "x": 373.6393990936745,
                "y": 199.63250937307023
            },
            {
                "x": 384.19697818634097,
                "y": 201.941979799591
            },
            {
                "x": 390.3005785992887,
                "y": 204.5813745727576
            },
            {
                "x": 402.34281725186133,
                "y": 208.3755045591846
            },
            {
                "x": 408.9413041847779,
                "y": 209.530239772445
            },
            {
                "x": 416.6945263309548,
                "y": 212.3345967189345
            },
            {
                "x": 422.3032402239338,
                "y": 214.31414279880946
            },
            {
                "x": 429.06668933017323,
                "y": 217.2834619186219
            },
            {
                "x": 432.8608193166002,
                "y": 219.26300799849685
            },
            {
                "x": 439.78923059616255,
                "y": 223.7169866782155
            },
            {
                "x": 445.89283100911035,
                "y": 228.50088970457998
            },
            {
                "x": 450.6767340354748,
                "y": 232.45998186432988
            },
            {
                "x": 455.6255992351622,
                "y": 237.24388489069435
            },
            {
                "x": 460.9043887814954,
                "y": 241.03801487712133
            },
            {
                "x": 466.6780648477974,
                "y": 244.1722961702567
            },
            {
                "x": 471.132043527516,
                "y": 246.9766531167462
            },
            {
                "x": 476.0809087272034,
                "y": 250.44085875652738
            },
            {
                "x": 479.54511436698454,
                "y": 253.08025352969398
            },
            {
                "x": 484.1640552200261,
                "y": 256.54445916947515
            },
            {
                "x": 488.123147379776,
                "y": 259.34881611596467
            },
            {
                "x": 492.41216388617175,
                "y": 264.46264348897495
            },
            {
                "x": 494.5566721393696,
                "y": 267.4319626087874
            }
        ],
        "rectMask": {
            "xMin": 363.24678217433103,
            "yMin": 193.36394678679954,
            "width": 140.7127338444446,
            "height": 78.6869566750294
        },
        "labels": {
            "labelName": "unnamed",
            "labelColor": "red",
            "labelColorRGB": "255,0,0",
            "visibility": false
        },
        "labelLocation": {
            "x": 433.60314909655335,
            "y": 232.70742512431426
        },
        "contentType": "polygon"
    }
]