[
    {
        "content": [
            {
                "x": 408.85491073583484,
                "y": 237.41679839996002
            },
            {
                "x": 408.47991073583484,
                "y": 236.54179839996002
            },
            {
                "x": 407.22991073583484,
                "y": 236.29179839996002
            },
            {
                "x": 404.72991073583484,
                "y": 236.66679839996002
            },
            {
                "x": 401.72991073583484,
                "y": 236.66679839996002
            },
            {
                "x": 400.85491073583484,
                "y": 235.91679839996002
            },
            {
                "x": 398.72991073583484,
                "y": 235.16679839996002
            },
            {
                "x": 397.10491073583484,
                "y": 234.41679839996002
            },
            {
                "x": 396.10491073583484,
                "y": 233.66679839996002
            },
            {
                "x": 394.97991073583484,
                "y": 233.66679839996002
            },
            {
                "x": 394.97991073583484,
                "y": 235.41679839996002
            },
            {
                "x": 395.97991073583484,
                "y": 236.29179839996002
            },
            {
                "x": 397.47991073583484,
                "y": 237.04179839996002
            },
            {
                "x": 399.85491073583484,
                "y": 237.79179839996002
            },
            {
                "x": 402.72991073583484,
                "y": 238.54179839996002
            },
            {
                "x": 405.85491073583484,
                "y": 238.79179839996002
            },
            {
                "x": 407.60491073583484,
                "y": 238.54179839996002
            }
        ],
        "rectMask": {
            "xMin": 394.97991073583484,
            "yMin": 233.66679839996002,
            "width": 13.875,
            "height": 5.125
        },
        "labels": {
            "labelName": "unnamed",
            "labelColor": "red",
            "labelColorRGB": "255,0,0",
            "visibility": false
        },
        "labelLocation": {
            "x": 401.91741073583484,
            "y": 236.22929839996002
        },
        "contentType": "polygon"
    }
]