[
    {
        "content": [
            {
                "x": 532.7630015792807,
                "y": 422.54175676483214
            },
            {
                "x": 528.5122973997305,
                "y": 425.0421709880969
            },
            {
                "x": 530.7626702006688,
                "y": 426.66744023321905
            },
            {
                "x": 535.6384779360352,
                "y": 427.0425023667088
            },
            {
                "x": 539.2640785597691,
                "y": 427.0425023667088
            },
            {
                "x": 542.8896791835032,
                "y": 428.2927094783412
            },
            {
                "x": 549.2657354528284,
                "y": 429.5429165899736
            },
            {
                "x": 552.141211809583,
                "y": 429.5429165899736
            },
            {
                "x": 556.2668952779699,
                "y": 429.6679373011368
            },
            {
                "x": 559.3924130570508,
                "y": 428.0426680560147
            },
            {
                "x": 559.3924130570508,
                "y": 425.5422538327499
            },
            {
                "x": 556.2668952779699,
                "y": 425.41723312158666
            },
            {
                "x": 553.5164396323786,
                "y": 426.04233667740283
            },
            {
                "x": 550.0158597198078,
                "y": 425.9173159662396
            },
            {
                "x": 548.1405490523592,
                "y": 424.79212956577044
            },
            {
                "x": 546.5152798072371,
                "y": 423.54192245413805
            },
            {
                "x": 544.2649070062988,
                "y": 422.54175676483214
            },
            {
                "x": 541.0143685160546,
                "y": 421.5415910755262
            },
            {
                "x": 536.5136229141779,
                "y": 421.5415910755262
            }
        ],
        "rectMask": {
            "xMin": 528.5122973997305,
            "yMin": 421.5415910755262,
            "width": 30.880115657320324,
            "height": 8.126346225610611
        },
        "labels": {
            "labelName": "unnamed",
            "labelColor": "red",
            "labelColorRGB": "255,0,0",
            "visibility": false
        },
        "labelLocation": {
            "x": 543.9523552283907,
            "y": 425.6047641883315
        },
        "contentType": "polygon"
    }
]