[
    {
        "content": [
            {
                "x": 697.0942629701889,
                "y": 408.00440033042014
            },
            {
                "x": 694.0942629701889,
                "y": 407.50440033042014
            },
            {
                "x": 690.5942629701889,
                "y": 407.12940033042014
            },
            {
                "x": 687.5942629701889,
                "y": 407.00440033042014
            },
            {
                "x": 684.5942629701889,
                "y": 406.25440033042014
            },
            {
                "x": 680.9692629701889,
                "y": 405.75440033042014
            },
            {
                "x": 677.0942629701889,
                "y": 404.50440033042014
            },
            {
                "x": 674.2192629701889,
                "y": 402.50440033042014
            },
            {
                "x": 671.2192629701889,
                "y": 397.62940033042014
            },
            {
                "x": 670.3442629701889,
                "y": 395.00440033042014
            },
            {
                "x": 669.4692629701889,
                "y": 392.50440033042014
            },
            {
                "x": 669.4692629701889,
                "y": 390.25440033042014
            },
            {
                "x": 668.9692629701889,
                "y": 387.50440033042014
            },
            {
                "x": 669.8442629701889,
                "y": 384.62940033042014
            },
            {
                "x": 671.2192629701889,
                "y": 382.50440033042014
            },
            {
                "x": 673.0942629701889,
                "y": 380.75440033042014
            },
            {
                "x": 675.0942629701889,
                "y": 378.62940033042014
            },
            {
                "x": 676.9692629701889,
                "y": 376.37940033042014
            },
            {
                "x": 678.8442629701889,
                "y": 374.25440033042014
            },
            {
                "x": 680.9692629701889,
                "y": 372.37940033042014
            },
            {
                "x": 682.4692629701889,
                "y": 370.25440033042014
            },
            {
                "x": 683.5942629701889,
                "y": 368.75440033042014
            },
            {
                "x": 685.4692629701889,
                "y": 366.62940033042014
            },
            {
                "x": 685.9692629701889,
                "y": 364.37940033042014
            },
            {
                "x": 684.8442629701889,
                "y": 363.12940033042014
            },
            {
                "x": 682.3442629701889,
                "y": 364.50440033042014
            },
            {
                "x": 681.0942629701889,
                "y": 366.37940033042014
            },
            {
                "x": 679.5942629701889,
                "y": 368.25440033042014
            },
            {
                "x": 678.0942629701889,
                "y": 369.75440033042014
            },
            {
                "x": 676.3442629701889,
                "y": 372.37940033042014
            },
            {
                "x": 673.8442629701889,
                "y": 374.12940033042014
            },
            {
                "x": 672.0942629701889,
                "y": 376.12940033042014
            },
            {
                "x": 671.3442629701889,
                "y": 377.37940033042014
            },
            {
                "x": 670.2192629701889,
                "y": 379.25440033042014
            },
            {
                "x": 668.9692629701889,
                "y": 381.37940033042014
            },
            {
                "x": 668.0942629701889,
                "y": 382.62940033042014
            },
            {
                "x": 666.8442629701889,
                "y": 384.62940033042014
            },
            {
                "x": 666.3442629701889,
                "y": 386.62940033042014
            },
            {
                "x": 666.3442629701889,
                "y": 389.37940033042014
            },
            {
                "x": 666.7192629701889,
                "y": 392.12940033042014
            },
            {
                "x": 667.3442629701889,
                "y": 393.87940033042014
            },
            {
                "x": 667.8442629701889,
                "y": 395.87940033042014
            },
            {
                "x": 668.3442629701889,
                "y": 398.25440033042014
            },
            {
                "x": 669.3442629701889,
                "y": 401.50440033042014
            },
            {
                "x": 670.2192629701889,
                "y": 403.50440033042014
            },
            {
                "x": 671.7192629701889,
                "y": 404.75440033042014
            },
            {
                "x": 674.0942629701889,
                "y": 405.87940033042014
            },
            {
                "x": 676.0942629701889,
                "y": 406.62940033042014
            },
            {
                "x": 677.8442629701889,
                "y": 407.37940033042014
            },
            {
                "x": 680.8442629701889,
                "y": 408.12940033042014
            },
            {
                "x": 682.0942629701889,
                "y": 408.62940033042014
            },
            {
                "x": 684.3442629701889,
                "y": 409.00440033042014
            },
            {
                "x": 685.9692629701889,
                "y": 409.00440033042014
            },
            {
                "x": 688.5942629701889,
                "y": 409.62940033042014
            },
            {
                "x": 691.3442629701889,
                "y": 409.62940033042014
            },
            {
                "x": 694.8442629701889,
                "y": 409.75440033042014
            },
            {
                "x": 696.5942629701889,
                "y": 409.50440033042014
            }
        ],
        "rectMask": {
            "xMin": 666.3442629701889,
            "yMin": 363.12940033042014,
            "width": 30.75,
            "height": 46.625
        },
        "labels": {
            "labelName": "unnamed",
            "labelColor": "red",
            "labelColorRGB": "255,0,0",
            "visibility": false
        },
        "labelLocation": {
            "x": 681.7192629701889,
            "y": 386.44190033042014
        },
        "contentType": "polygon"
    }
]