[
    {
        "content": [
            {
                "x": 719.1294564016544,
                "y": 249.12377226951156
            },
            {
                "x": 718.7544564016544,
                "y": 251.24877226951156
            },
            {
                "x": 718.7544564016544,
                "y": 252.49877226951156
            },
            {
                "x": 718.7544564016544,
                "y": 255.74877226951156
            },
            {
                "x": 719.1294564016544,
                "y": 257.99877226951156
            },
            {
                "x": 719.8794564016544,
                "y": 260.74877226951156
            },
            {
                "x": 720.6294564016544,
                "y": 263.24877226951156
            },
            {
                "x": 721.7544564016544,
                "y": 266.24877226951156
            },
            {
                "x": 722.8794564016544,
                "y": 267.87377226951156
            },
            {
                "x": 723.8794564016544,
                "y": 269.99877226951156
            },
            {
                "x": 724.3794564016544,
                "y": 272.62377226951156
            },
            {
                "x": 725.1294564016544,
                "y": 274.99877226951156
            },
            {
                "x": 726.2544564016544,
                "y": 278.37377226951156
            },
            {
                "x": 727.3794564016544,
                "y": 281.74877226951156
            },
            {
                "x": 728.5044564016544,
                "y": 285.49877226951156
            },
            {
                "x": 729.2544564016544,
                "y": 290.37377226951156
            },
            {
                "x": 729.2544564016544,
                "y": 293.37377226951156
            },
            {
                "x": 729.6294564016544,
                "y": 298.62377226951156
            },
            {
                "x": 730.1294564016544,
                "y": 303.62377226951156
            },
            {
                "x": 731.0044564016544,
                "y": 306.74877226951156
            },
            {
                "x": 730.2544564016544,
                "y": 308.99877226951156
            },
            {
                "x": 730.1294564016544,
                "y": 311.12377226951156
            },
            {
                "x": 729.3794564016544,
                "y": 312.74877226951156
            },
            {
                "x": 727.8794564016544,
                "y": 315.24877226951156
            },
            {
                "x": 727.5044564016544,
                "y": 316.49877226951156
            },
            {
                "x": 726.1294564016544,
                "y": 318.62377226951156
            },
            {
                "x": 723.7544564016544,
                "y": 320.62377226951156
            },
            {
                "x": 722.6294564016544,
                "y": 321.62377226951156
            },
            {
                "x": 720.3794564016544,
                "y": 323.49877226951156
            },
            {
                "x": 717.8794564016544,
                "y": 326.12377226951156
            },
            {
                "x": 716.6294564016544,
                "y": 327.37377226951156
            },
            {
                "x": 714.3794564016544,
                "y": 329.49877226951156
            },
            {
                "x": 713.2544564016544,
                "y": 331.37377226951156
            },
            {
                "x": 711.0044564016544,
                "y": 332.87377226951156
            },
            {
                "x": 709.1294564016544,
                "y": 334.49877226951156
            },
            {
                "x": 709.2544564016544,
                "y": 336.74877226951156
            },
            {
                "x": 710.0044564016544,
                "y": 337.12377226951156
            },
            {
                "x": 712.5044564016544,
                "y": 337.37377226951156
            },
            {
                "x": 713.6294564016544,
                "y": 336.99877226951156
            },
            {
                "x": 715.6294564016544,
                "y": 335.24877226951156
            },
            {
                "x": 718.2544564016544,
                "y": 333.37377226951156
            },
            {
                "x": 720.0044564016544,
                "y": 331.12377226951156
            },
            {
                "x": 721.8794564016544,
                "y": 328.87377226951156
            },
            {
                "x": 725.7544564016544,
                "y": 326.62377226951156
            },
            {
                "x": 728.6294564016544,
                "y": 323.24877226951156
            },
            {
                "x": 730.1294564016544,
                "y": 319.87377226951156
            },
            {
                "x": 732.5044564016544,
                "y": 316.37377226951156
            },
            {
                "x": 733.5044564016544,
                "y": 314.12377226951156
            },
            {
                "x": 734.0044564016544,
                "y": 311.12377226951156
            },
            {
                "x": 734.6294564016544,
                "y": 307.74877226951156
            },
            {
                "x": 734.7544564016544,
                "y": 304.49877226951156
            },
            {
                "x": 734.7544564016544,
                "y": 302.12377226951156
            },
            {
                "x": 733.8794564016544,
                "y": 296.99877226951156
            },
            {
                "x": 733.8794564016544,
                "y": 294.24877226951156
            },
            {
                "x": 734.0044564016544,
                "y": 291.37377226951156
            },
            {
                "x": 733.6294564016544,
                "y": 287.99877226951156
            },
            {
                "x": 733.5044564016544,
                "y": 285.24877226951156
            },
            {
                "x": 732.7544564016544,
                "y": 281.49877226951156
            },
            {
                "x": 732.0044564016544,
                "y": 276.24877226951156
            },
            {
                "x": 731.7544564016544,
                "y": 273.99877226951156
            },
            {
                "x": 730.8794564016544,
                "y": 270.37377226951156
            },
            {
                "x": 729.1294564016544,
                "y": 266.49877226951156
            },
            {
                "x": 728.7544564016544,
                "y": 263.62377226951156
            },
            {
                "x": 726.7544564016544,
                "y": 259.87377226951156
            },
            {
                "x": 725.3794564016544,
                "y": 256.49877226951156
            },
            {
                "x": 725.2544564016544,
                "y": 254.12377226951156
            },
            {
                "x": 725.2544564016544,
                "y": 251.99877226951156
            },
            {
                "x": 723.8794564016544,
                "y": 249.99877226951156
            },
            {
                "x": 720.8794564016544,
                "y": 248.87377226951156
            }
        ],
        "rectMask": {
            "xMin": 709.1294564016544,
            "yMin": 248.87377226951156,
            "width": 25.625,
            "height": 88.5
        },
        "labels": {
            "labelName": "unnamed",
            "labelColor": "red",
            "labelColorRGB": "255,0,0",
            "visibility": false
        },
        "labelLocation": {
            "x": 721.9419564016544,
            "y": 293.12377226951156
        },
        "contentType": "polygon"
    }
]