[
    {
        "content": [
            {
                "x": 578.7352490110146,
                "y": 525.3348512467237
            },
            {
                "x": 579.6102490110146,
                "y": 521.5848512467237
            },
            {
                "x": 580.1102490110146,
                "y": 517.2098512467237
            },
            {
                "x": 581.2352490110146,
                "y": 512.0848512467237
            },
            {
                "x": 580.4852490110146,
                "y": 509.4598512467237
            },
            {
                "x": 578.2352490110146,
                "y": 511.0848512467237
            },
            {
                "x": 576.6102490110146,
                "y": 515.8348512467237
            },
            {
                "x": 574.1102490110146,
                "y": 521.4598512467237
            },
            {
                "x": 572.2352490110146,
                "y": 527.2098512467237
            },
            {
                "x": 571.1102490110146,
                "y": 534.2098512467237
            },
            {
                "x": 570.2352490110146,
                "y": 540.4598512467237
            },
            {
                "x": 570.6102490110146,
                "y": 543.5848512467237
            },
            {
                "x": 572.7352490110146,
                "y": 544.2098512467237
            },
            {
                "x": 574.4852490110146,
                "y": 541.5848512467237
            },
            {
                "x": 575.7352490110146,
                "y": 537.8348512467237
            },
            {
                "x": 576.2352490110146,
                "y": 533.8348512467237
            },
            {
                "x": 577.9852490110146,
                "y": 530.5848512467237
            },
            {
                "x": 578.7352490110146,
                "y": 528.4598512467237
            }
        ],
        "rectMask": {
            "xMin": 570.2352490110146,
            "yMin": 509.4598512467237,
            "width": 11,
            "height": 34.75
        },
        "labels": {
            "labelName": "unnamed",
            "labelColor": "red",
            "labelColorRGB": "255,0,0",
            "visibility": false
        },
        "labelLocation": {
            "x": 575.7352490110146,
            "y": 526.8348512467237
        },
        "contentType": "polygon"
    }
]